sanic_toolbox/__init__.py
sanic_toolbox/blueprint.py
sanic_toolbox/exceptions.py
sanic_toolbox/lazyapp.py
sanic_toolbox/utils.py
sanic_toolbox/view.py
sanic_toolbox-0.5.0.dist-info/METADATA
sanic_toolbox-0.5.0.dist-info/RECORD
sanic_toolbox-0.5.0.dist-info/WHEEL
sanic_toolbox-0.5.0.dist-info/top_level.txt
