Metadata-Version: 2.1
Name: sanic-toolbox
Version: 0.5.0
Summary: A general utility toolbox for Sanic without monkey patching, for plugins and applications
Home-page: https://github.com/vltr/sanic-toolbox
Author: Richard Kuesters
Author-email: rkuesters@gmail.com
License: MIT
Download-URL: https://github.com/vltr/sanic-toolbox/archive/master.zip
Project-URL: Bug Reports, https://github.com/vltr/sanic-toolbox/issues
Project-URL: Source, https://github.com/vltr/sanic-toolbox
Keywords: sanic toolbox utils lazy-evaluation productivity
Platform: UNKNOWN
Classifier: Development Status :: 4 - Beta
Classifier: Intended Audience :: Developers
Classifier: License :: OSI Approved :: MIT License
Classifier: Programming Language :: Python :: 3 :: Only
Classifier: Programming Language :: Python :: 3.5
Classifier: Programming Language :: Python :: 3.6
Provides-Extra: all
Provides-Extra: tests
Provides-Extra: docs
Provides-Extra: all
Requires-Dist: Sphinx; extra == 'all'
Requires-Dist: coverage; extra == 'all'
Requires-Dist: pytest-cov; extra == 'all'
Requires-Dist: pytest-flakes; extra == 'all'
Requires-Dist: pytest-pep8; extra == 'all'
Requires-Dist: pytest-asyncio; extra == 'all'
Requires-Dist: pytest; extra == 'all'
Requires-Dist: sanic; extra == 'all'
Requires-Dist: codecov; extra == 'all'
Requires-Dist: Sphinx; extra == 'all'
Requires-Dist: coverage; extra == 'all'
Requires-Dist: pytest-cov; extra == 'all'
Requires-Dist: pytest-flakes; extra == 'all'
Requires-Dist: pytest-pep8; extra == 'all'
Requires-Dist: pytest-asyncio; extra == 'all'
Requires-Dist: pytest; extra == 'all'
Requires-Dist: sanic; extra == 'all'
Requires-Dist: codecov; extra == 'all'
Provides-Extra: docs
Requires-Dist: Sphinx; extra == 'docs'
Provides-Extra: tests
Requires-Dist: coverage; extra == 'tests'
Requires-Dist: pytest-cov; extra == 'tests'
Requires-Dist: pytest-flakes; extra == 'tests'
Requires-Dist: pytest-pep8; extra == 'tests'
Requires-Dist: pytest-asyncio; extra == 'tests'
Requires-Dist: pytest; extra == 'tests'
Requires-Dist: sanic; extra == 'tests'
Requires-Dist: codecov; extra == 'tests'
